ethsnarks/__init__.py
ethsnarks/eddsa.py
ethsnarks/evmasm.py
ethsnarks/field.py
ethsnarks/jubjub.py
ethsnarks/merkletree.py
ethsnarks/numbertheory.py
ethsnarks/pedersen.py
ethsnarks/r1cs.py
ethsnarks/sha3.py
ethsnarks/shamirspoly.py
ethsnarks/utils.py
ethsnarks/verifier.py
ethsnarks/cli/__init__.py
ethsnarks/cli/proof2sol.py
ethsnarks/cli/utils.py
ethsnarks/cli/verify.py
ethsnarks/cli/vk2sol.py
ethsnarks/mimc/__init__.py
ethsnarks/mimc/contract.py
ethsnarks/mimc/contract_sol.py
ethsnarks/mimc/permutation.py
ethsnarks/poseidon/__init__.py
ethsnarks/poseidon/contract.py
ethsnarks/poseidon/permutation.py
ethsnarks-0.0.1.dist-info/AUTHORS
ethsnarks-0.0.1.dist-info/LICENSE
ethsnarks-0.0.1.dist-info/METADATA
ethsnarks-0.0.1.dist-info/WHEEL
ethsnarks-0.0.1.dist-info/top_level.txt
ethsnarks-0.0.1.dist-info/RECORD
