Metadata-Version: 2.1
Name: ethsnarks
Version: 0.0.1
Summary: Python library for ethsnarks
Home-page: https://github.com/HarryR/ethsnarks-python
Author: HarryR
License: UNKNOWN
Platform: UNKNOWN
Classifier: Programming Language :: Python :: 3
Classifier: License :: OSI Approved :: GNU Library or Lesser General Public License (LGPL)
Classifier: Operating System :: OS Independent
Requires-Dist: py-ecc
Requires-Dist: bitstring
Requires-Dist: pysha3
Requires-Dist: pyblake2
